sdkconf/__init__.py
sdkconf/_version.py
sdkconf/templates/sdkconf/python/conf
sdkconf/templates/sdkconf/python/install
sdkconf/templates/sdkconf/python/verify
sdkconf-2024.11.19.1.dist-info/AUTHORS
sdkconf-2024.11.19.1.dist-info/LICENSE
sdkconf-2024.11.19.1.dist-info/METADATA
sdkconf-2024.11.19.1.dist-info/WHEEL
sdkconf-2024.11.19.1.dist-info/top_level.txt
sdkconf-2024.11.19.1.dist-info/RECORD
